labelgenius/LabelGenius.py
labelgenius/__init__.py
labelgenius-0.1.6.dist-info/licenses/LICENSE
labelgenius-0.1.6.dist-info/METADATA
labelgenius-0.1.6.dist-info/WHEEL
labelgenius-0.1.6.dist-info/top_level.txt
labelgenius-0.1.6.dist-info/RECORD
