Metadata-Version: 2.4
Name: labelgenius
Version: 0.1.6
Summary: Flexible GPT + CLIP classification toolkit for multimodal labeling
Author-email: "Jiacheng Huang, M.S." <huan1660@umn.edu>, "Zhongxing Zhang, M.S." <zhan8889@umn.edu>, "Chris Chao Su, Ph.D." <suchao@bu.edu>
License: MIT
Project-URL: Homepage, https://github.com/mediaccs/LabelGenius
Project-URL: Repository, https://github.com/mediaccs/LabelGenius
Project-URL: Issues, https://github.com/mediaccs/LabelGenius/issues
Keywords: gpt,clip,classification,multimodal,llm,openai,vision,research
Classifier: Programming Language :: Python :: 3
Classifier: Programming Language :: Python :: 3.9
Classifier: License :: OSI Approved :: MIT License
Classifier: Operating System :: OS Independent
Classifier: Intended Audience :: Science/Research
Classifier: Topic :: Scientific/Engineering :: Artificial Intelligence
Requires-Python: >=3.9
License-File: LICENSE
Requires-Dist: torch>=2.0.0
Requires-Dist: transformers>=4.30.0
Requires-Dist: pandas
Requires-Dist: numpy
Requires-Dist: tqdm
Requires-Dist: pillow
Requires-Dist: sqlitedict
Requires-Dist: loguru
Requires-Dist: openai>=1.0.0
Requires-Dist: scikit-learn
Requires-Dist: torchvision
Dynamic: license-file
